{"last_updated_epoch": 1644766200, "last_updated": "2022-02-13 10:30", "temp_c": -19.0, "temp_f": -2.2, "is_day": 1, "condition": {"text": "Sunny", "icon": "//cdn.weatherapi.com/weather/64x64/day/113.png", "code": 1000}, "wind_mph": 6.9, "wind_kph": 11.2, "wind_degree": 40, "wind_dir": "NE", "pressure_mb": 1029.0, "pressure_in": 30.38, "precip_mm": 0.0, "precip_in": 0.0, "humidity": 54, "cloud": 0, "feelslike_c": -26.8, "feelslike_f": -16.2, "vis_km": 14.0, "vis_miles": 8.0, "uv": 2.0, "gust_mph": 11.0, "gust_kph": 17.6}